pyRealEstate/Pre_Processing.py
pyRealEstate/RealEstateMetrics.py
pyRealEstate/Time_Trending.py
pyRealEstate/__init__.py
pyRealEstate-0.1.9.dist-info/LICENSE
pyRealEstate-0.1.9.dist-info/METADATA
pyRealEstate-0.1.9.dist-info/WHEEL
pyRealEstate-0.1.9.dist-info/top_level.txt
pyRealEstate-0.1.9.dist-info/RECORD
