Metadata-Version: 2.1
Name: pyRealEstate
Version: 0.1.9
Summary: package to assist with data analytics in real estate
Home-page: https://github.com/Joshua-Data-Wizard/PyRealEstate/tree/main
Author: Joshua Jorgensen
License: MIT License
Project-URL: Homepage, https://github.com/Joshua-Data-Wizard/PyRealEstate/tree/main
Project-URL: Bug Reports, https://github.com/Joshua-Data-Wizard/PyRealEstate/tree/main
Project-URL: Source, https://github.com/Joshua-Data-Wizard/PyRealEstate/tree/main
Classifier: Programming Language :: Python :: 3
Classifier: License :: OSI Approved :: MIT License
Classifier: Operating System :: OS Independent
Requires-Python: >=3.6
License-File: LICENSE
Requires-Dist: scikit-learn
Requires-Dist: numpy
Requires-Dist: pandas
Requires-Dist: statsmodels
Requires-Dist: matplotlib
Requires-Dist: lightgbm
Requires-Dist: scipy
